nmosreverseproxy/__init__.py
nmosreverseproxy/proxylisting.py
nmosreverseproxy/proxylistingservice.py
usr/bin/proxylisting
nmosreverseproxy-0.6.0.dist-info/LICENSE.md
nmosreverseproxy-0.6.0.dist-info/METADATA
nmosreverseproxy-0.6.0.dist-info/NOTICE.md
nmosreverseproxy-0.6.0.dist-info/WHEEL
nmosreverseproxy-0.6.0.dist-info/top_level.txt
nmosreverseproxy-0.6.0.dist-info/RECORD
