Metadata-Version: 2.1
Name: nmosreverseproxy
Version: 0.6.0
Summary: Reverse Proxy Directory listing service and Apache 2 configuration for NMOS services
Home-page: https://github.com/bbc/nmos-reverse-proxy
Author: Simon Rankine
Author-email: Simon.Rankine@bbc.co.uk
License: Apache 2
Platform: UNKNOWN
Requires-Dist: six
Requires-Dist: nmoscommon
